skbold/__init__.py
skbold/core/__init__.py
skbold/core/convert_to_epi.py
skbold/core/convert_to_mni.py
skbold/core/mvp.py
skbold/core/mvp_between.py
skbold/core/mvp_within.py
skbold/core/tests/__init__.py
skbold/core/tests/test_convert2epi.py
skbold/core/tests/test_mvp_between.py
skbold/core/tests/test_mvp_within.py
skbold/data/Feat_single_trial_template.fsf
skbold/data/Melodic_template.fsf
skbold/data/ROIs/MNI152_2mm.nii.gz
skbold/data/ROIs/HarvardOxford-Cortical/HarvardOxford-Cortical-Lateralized.xml
skbold/data/ROIs/HarvardOxford-Cortical/HarvardOxford-Cortical.xml
skbold/data/ROIs/HarvardOxford-Cortical/HarvardOxford-cort-bilateral-prob-2mm.nii.gz
skbold/data/ROIs/HarvardOxford-Cortical/HarvardOxford-cort-lateralized-prob-2mm.nii.gz
skbold/data/ROIs/HarvardOxford-Subcortical/HarvardOxford-Subcortical.xml
skbold/data/ROIs/HarvardOxford-Subcortical/HarvardOxford-sub-bilateral-prob-2mm.nii.gz
skbold/data/ROIs/HarvardOxford-Subcortical/HarvardOxford-sub-lateralized-prob-2mm.nii.gz
skbold/data/ROIs/Yeo2011/Yeo_7networks_conservative_2mm.nii.gz
skbold/data/ROIs/Yeo2011/Yeo_7networks_liberal_2mm.nii.gz
skbold/data/ROIs/other/GrayMatter_prob.nii.gz
skbold/data/ROIs/other/VentricleMask.nii.gz
skbold/data/ROIs/tissuepriors/avg152T1_csf.nii.gz
skbold/data/ROIs/tissuepriors/avg152T1_gray.nii.gz
skbold/data/ROIs/tissuepriors/avg152T1_white.nii.gz
skbold/data/test_data/sample_behav.tsv
skbold/data/test_data/mock_subjects/sub001/.gitkeep
skbold/data/test_data/mock_subjects/sub002/.gitkeep
skbold/data/test_data/mock_subjects/sub003/.gitkeep
skbold/data/test_data/mock_subjects/sub004/.gitkeep
skbold/data/test_data/mock_subjects/sub005/.gitkeep
skbold/data/test_data/mock_subjects/sub006/.gitkeep
skbold/data/test_data/mock_subjects/sub007/.gitkeep
skbold/data/test_data/mock_subjects/sub008/.gitkeep
skbold/data/test_data/mock_subjects/sub009/.gitkeep
skbold/data/test_data/preprocessed/sub_001/mytask/conditionA_trial1.bfsl
skbold-0.3.3.dist-info/DESCRIPTION.rst
skbold-0.3.3.dist-info/METADATA
skbold-0.3.3.dist-info/RECORD
skbold-0.3.3.dist-info/WHEEL
skbold-0.3.3.dist-info/metadata.json
skbold-0.3.3.dist-info/top_level.txt
