Metadata-Version: 2.0
Name: skbold
Version: 0.3.3
Summary: Utilities and tools for machine learning on BOLD-fMRI data.
Home-page: http://skbold.readthedocs.io/en/latest/
Author: Lukas Snoek
Author-email: lukassnoek@gmail.com
License: MIT
Keywords: fMRI MVPA decoding machine learning
Platform: Linux
Classifier: Development Status :: 2 - Pre-Alpha
Classifier: Intended Audience :: Science/Research
Classifier: Operating System :: POSIX :: Linux
Classifier: Programming Language :: Python :: 2.7
Classifier: Topic :: Scientific/Engineering :: Bio-Informatics
Requires-Dist: configparser
Requires-Dist: funcsigs
Requires-Dist: future
Requires-Dist: nibabel (>=2.0)
Requires-Dist: numpy (>=1.10)
Requires-Dist: pandas (>=0.17)
Requires-Dist: scikit-learn (>=0.18)
Requires-Dist: scipy (>=0.17)
